uniprocessor/macros/define.v
`define RstEnable  	1'b0	// Reset whilst signal '0'
`define RstDisable 	1'b1 
`define ZeroWord   	32'h0000_0000 
`define ZeroDoubleWord  64'h0000_0000_0000_0000
`define WriteEnable 	1'b1
`define WriteDisable	1'b0
`define ReadEnable	1'b1
`define ReadDisable	1'b0

`define AluControlIn	3:0	// The size of ALU Operation, i.e., ALU control input

`define InstValid	1'b0	// Valid instruction
`define InstInvalid	1'b1	// Invalid instruction
`define True_v		1'b1	// Logically True
`define False_v		1'b0	// Logically False
`define ChipEnable	1'b1
`define ChipDisable	1'b0

// The marcos of RV32I Based instruction
// The 7-bit opcode
`define EXE_ORI	 7'b0_0100_11 // ori 
`define EXE_NOP	 7'b0_0000_00 // nop
`define EXE_BEQ  7'b1_1000_11 // beq
`define EXE_BNE  7'b1_1000_11 // bne
`define EXE_BLT  7'b1_1000_11 // blt
`define EXE_BGE  7'b1_1000_11 // bge
`define EXE_BLTU 7'b1_1000_11 // bltu
`define EXE_BGEU 7'b1_1000_11 // bgeu

`define EXE_ORI 7'b0_0100_11 // ori

// Instruction Memory (ROM) 
`define InstAddrBus 31:0
`define InstAddrWidth 32
`define InstWidth 32
`define InstBus 31:0
`define InstMemNum 131071 // The actual size of ROM is 128KB
`define InstMemNumLog2 17 // The actual size of address

// Register File: regfile
`define RegAddrBus 4:0 // The size of address bus, i.e., 5
`define RegBus 63:0 	   // The size of data bus is 64-bit
`define RegWidth 64      // The data size of each register is 64-bit
`define DoubleRegWidth 128
`define DoubleRegBus 127:0
`define RegNum 32 //  The register from x0 to x31
`define RegNumLog2 5 // The size of address bus, i.e., log 32 base 2 = 5
`define NOPRegAddr 5'b0_0000

uniprocessor/Pipeline/if_id.v
`include "../macros/define.v"

module if_id (
	input wire sys_clk,
	input wire rstn,

	input wire [`InstAddrBus] pc_addr_if, // The address of currently fetched instruction (from the result of instruction fetching step) 
	input wire [`InstBus]     fetched_inst_if // The instruction fetched at any clock cycle

	output reg [`InstAddrBus] pc_addr_id, // The address of currnetly fetched instruction (to instruction decoding step)
	output reg [`InstBus] fetched_inst_id // The fetched instruction to instruction decoder
);

	always @(posedge sys_clk, rstn) begin
		if(rstn == `RstEnable) begin
			pc_addr_id[`InstAddrBus]  <= `ZeroWord; // The output of program counter is set as '0' whilst the reset state is set
			fetched_inst_id[`InstBus] <= `ZeroWord; // The instruction is '0' when the reset state is set
		end 
		else begin
			pc_addr_id[`InstAddrBus]  <= pc_addr_if[`InstAddrBus];  // Pass the current instruction addree to IF/ID register 
			fetched_inst_id[`InstBus] <= fetched_inst_if[`InstBus]; // Pass the currently fetched instruciton to IF/ID register
		end
	end
endmodule

uniprocessor/MEM/InstMem_controller.v
`include "../macros/define.v" 

// Read requested memory address and output its corresponding instruction from instruction memory	
module InstMem_controller (
	input wire ce,                      // Start replying the request when ce signal is enable
	input wire [`InstAddrBus] inst_addr,

	output reg [`InstBus] inst
);

	reg [`InstBus] inst_mem[0:6];

	// Load all instructions from Instruction Memory (ROM).
	// The contents of instruction memory is defined by "Inst_mem.mem" file
	initial begin
		$display("Loading ROM");
		$readmemh("Inst_mem.mem", inst_mem);
	end

	wire [6:0] inst_mem_index;
	assign inst_mem_index = {2'b00, inst_addr[`InstWidth-1:2]};
	always @(*) begin
		if(ce == `ChipDisable) inst[`InstBus] <= `InstWidth'd0;
		else inst[`InstBus] <= inst_mem[inst_mem_index];
	end

endmodule

uniprocessor/PC/pc.v
`include "../macros/define.v"

module pc (
	
	input wire sys_clk,
	input wire rstn,

	output reg [`InstAddrBus] pc_addr, // Point the memory address of current instruction inside the instruction memory (32-bit instruction)
	output reg	 ce // Enable the instruction memory to be accessable 
);

	always@ (posedge sys_clk, rstn)
	begin
		if(rstn == `RstEnable) ce <= `ChipDisable;
		else		       ce <= `ChipEnable;
	end

	always@ (posedge sys_clk, rstn)
	begin
		if(rstn == `RstEnable && ce == `ChipDisable ) 
			pc_addr[`InstAddrBus] <= `InstAddrWidth'd0;
		else
			pc_addr[`InstAddrBus] <= pc_addr[`InstAddrBus] + 4'h4;
			
	end

endmodule

uniprocessor/Pipeline/tb_if_id.v
`timescale 1ns/100ps
`include "../macros/define.v" 

module tb_if_id;

	reg sys_clk, rstn;
    	wire ce;
	wire [`InstAddrBus] pc_addr;
	wire [`InstBus] inst;
	wire [`InstAddrBus] pc_addr_id;
	wire [`InstBus] fetched_inst_id;

	pc u0 (	
		 .sys_clk 	(sys_clk),
		 .rstn		(rstn),	
		 .pc_addr  (pc_addr[`InstAddrBus]), 
		 .ce          (ce)
	);

	InstMem_controller u1(
		.ce(ce),
		.inst_addr(pc_addr[`InstAddrBus]),
		.inst(inst[`InstBus])
	);
	
	if_id u2(
		 .sys_clk	        (sys_clk),
		 .rstn		        (rtsn),
		.pc_addr_if	    (pc_addr[`InstAddrBus]),       
		.fetched_inst_if  (inst[`InstBus]),
		.pc_addr_id	    (pc_addr_id[`InstAddrBus]),      
		.fetched_inst_id (fetched_inst_id[`InstBus]) 
	);

	initial begin
		$dumpfile("tb_if_id.vcd");
		$dumpvars(0, tb_if_id);
		$monitor("ce: %b, pc_addr: %h, inst: %h, pc_addr_id: %h, fetched_inst_id: %h", ce, pc_addr, inst, pc_addr_id, fetched_inst_id);
	end

	initial begin
		#0;
		rstn    <= `RstEnable;
		
		#100;
		rstn <= `RstDisable;

		#300 $finish;
	end

	initial begin
		#0;
		sys_clk <= 1'b0;

		forever #10 sys_clk <= ~sys_clk;
		
		#300 $finish;
	end

endmodule

uniprocessor/Pipeline/tb_if_id.vcd
$date
	Thu Nov 29 16:30:44 2018
$end
$version
	Icarus Verilog
$end
$timescale
	100ps
$end
$scope module tb_if_id $end
$var wire 1 ! rtsn $end
$var wire 32 " pc_addr_id [31:0] $end
$var wire 32 # pc_addr [31:0] $end
$var wire 32 $ inst [31:0] $end
$var wire 32 % fetched_inst_id [31:0] $end
$var wire 1 & ce $end
$var reg 1 ' rstn $end
$var reg 1 ( sys_clk $end
$scope module u0 $end
$var wire 1 ' rstn $end
$var wire 1 ( sys_clk $end
$var reg 1 & ce $end
$var reg 32 ) pc_addr [31:0] $end
$upscope $end
$scope module u1 $end
$var wire 1 & ce $end
$var wire 32 * inst_addr [31:0] $end
$var wire 7 + inst_mem_index [6:0] $end
$var reg 32 , inst [31:0] $end
$upscope $end
$scope module u2 $end
$var wire 32 - fetched_inst_if [31:0] $end
$var wire 32 . pc_addr_if [31:0] $end
$var wire 1 ! rstn $end
$var wire 1 ( sys_clk $end
$var reg 32 / fetched_inst_id [31:0] $end
$var reg 32 0 pc_addr_id [31:0] $end
$upscope $end
$upscope $end
$enddefinitions $end
#0
$dumpvars
bx 0
bx /
bx .
b0 -
b0 ,
bx +
bx *
bx )
0(
0'
0&
bx %
b0 $
bx #
bx "
z!
$end
#100
b0 +
b0 #
b0 )
b0 *
b0 .
b0 %
b0 /
1(
#200
0(
#300
b0 "
b0 0
1(
#400
0(
#500
1(
#600
0(
#700
1(
#800
0(
#900
1(
#1000
bx $
bx ,
bx -
b1 +
1&
b100 #
b100 )
b100 *
b100 .
0(
1'
#1100
b10 +
b1000 #
b1000 )
b1000 *
b1000 .
bx %
bx /
b100 "
b100 0
1(
#1200
0(
#1300
b11 +
b1100 #
b1100 )
b1100 *
b1100 .
b1000 "
b1000 0
1(
#1400
0(
#1500
b100 +
b10000 #
b10000 )
b10000 *
b10000 .
b1100 "
b1100 0
1(
#1600
0(
#1700
b101 +
b10100 #
b10100 )
b10100 *
b10100 .
b10000 "
b10000 0
1(
#1800
0(
#1900
b110 +
b11000 #
b11000 )
b11000 *
b11000 .
b10100 "
b10100 0
1(
#2000
0(
#2100
b111 +
b11100 #
b11100 )
b11100 *
b11100 .
b11000 "
b11000 0
1(
#2200
0(
#2300
b1000 +
b100000 #
b100000 )
b100000 *
b100000 .
b11100 "
b11100 0
1(
#2400
0(
#2500
b1001 +
b100100 #
b100100 )
b100100 *
b100100 .
b100000 "
b100000 0
1(
#2600
0(
#2700
b1010 +
b101000 #
b101000 )
b101000 *
b101000 .
b100100 "
b100100 0
1(
#2800
0(
#2900
b1011 +
b101100 #
b101100 )
b101100 *
b101100 .
b101000 "
b101000 0
1(
#3000
0(
#3100
b1100 +
b110000 #
b110000 )
b110000 *
b110000 .
b101100 "
b101100 0
1(
#3200
0(
#3300
b1101 +
b110100 #
b110100 )
b110100 *
b110100 .
b110000 "
b110000 0
1(
#3400
0(
#3500
b1110 +
b111000 #
b111000 )
b111000 *
b111000 .
b110100 "
b110100 0
1(
#3600
0(
#3700
b1111 +
b111100 #
b111100 )
b111100 *
b111100 .
b111000 "
b111000 0
1(
#3800
0(
#3900
b10000 +
b1000000 #
b1000000 )
b1000000 *
b1000000 .
b111100 "
b111100 0
1(
