uniprocessor/macros/define.v
`define RstEnable  	1'b0	// Reset whilst signal '0'
`define RstDisable 	1'b1 
`define ZeroWord   	32'h0000_0000 
`define ZeroDoubleWord  64'h0000_0000_0000_0000
`define WriteEnable 	1'b1
`define WriteDisable	1'b0
`define ReadEnable	1'b1
`define ReadDisable	1'b0

`define AluControlIn	3:0	// The size of ALU Operation, i.e., ALU control input

`define InstValid	1'b0	// Valid instruction
`define InstInvalid	1'b1	// Invalid instruction
`define True_v		1'b1	// Logically True
`define False_v		1'b0	// Logically False
`define ChipEnable	1'b1
`define ChipDisable	1'b0

// The marcos of RV32I Based instruction
// The 7-bit opcode
`define EXE_ORI	 7'b0_0100_11 // ori 
`define EXE_NOP	 7'b0_0000_00 // nop
`define EXE_BEQ  7'b1_1000_11 // beq
`define EXE_BNE  7'b1_1000_11 // bne
`define EXE_BLT  7'b1_1000_11 // blt
`define EXE_BGE  7'b1_1000_11 // bge
`define EXE_BLTU 7'b1_1000_11 // bltu
`define EXE_BGEU 7'b1_1000_11 // bgeu

`define EXE_ORI 7'b0_0100_11 // ori

// Instruction Memory (ROM) 
`define InstAddrBus 31:0
`define InstAddrWidth 32
`define InstWidth 32
`define InstBus 31:0
`define InstMemNum 131071 // The actual size of ROM is 128KB
`define InstMemNumLog2 17 // The actual size of address

// Register File: regfile
`define RegAddrBus 4:0 // The size of address bus, i.e., 5
`define RegBus 63:0 	   // The size of data bus is 64-bit
`define RegWidth 64      // The data size of each register is 64-bit
`define DoubleRegWidth 128
`define DoubleRegBus 127:0
`define RegNum 32 //  The register from x0 to x31
`define RegNumLog2 5 // The size of address bus, i.e., log 32 base 2 = 5
`define NOPRegAddr 5'b0_0000

uniprocessor/Pipeline/InstMem_controller.v
`include "../macros/define.v"

// Read requested memory address and output its corresponding instruction from instruction memory	
module InstMem_controller (
	input wire ce,                      // Start replying the request when ce signal is enable
	input wire [`InstAddrBus] inst_addr,

	output reg [`InstBus] inst
);

	reg [`InstBus] inst_mem[0:5];

	// Load all instructions from Instruction Memory (ROM).
	// The contents of instruction memory is defined by "Inst_mem.mem" file
	initial begin
		$display("Loading ROM");
		$readmemh("Inst_mem.mem", inst_mem);
	end

	wire [5:0] inst_mem_index;
	assign inst_mem_index = {2'b00, inst_addr[`InstWidth-1:2]};
	always @(*) begin
		if(ce == `ChipDisable) inst[`InstBus] <= `InstWidth'd0;
		else inst[`InstBus] <= inst_mem[inst_mem_index];
	end

endmodule

uniprocessor/Pipeline/tb_InstMem.v
`timescale 1ns/100ps
`include "../macros/define.v"

module tb_InstMem;

	reg ce;
	reg [`InstAddrBus] inst_addr;
	wire [`InstBus] inst;

	InstMem_controller u0(
		.ce(ce),
		.inst_addr(inst_addr[`InstAddrBus]),
		.inst(inst[`InstBus])
	);

	initial begin
		$dumpfile("tb_InstMem.vcd");
		$dumpvars(0, tb_InstMem);
		$monitor("ce = %b, inst_addr = %h, inst = %h", ce, inst_addr[`InstAddrBus], inst[`InstBus]);
	end

	initial begin
		#0;
		ce <= `ChipDisable;
		inst_addr[`InstAddrBus] <= `InstAddrWidth'd0;

		#10;
		ce <= `ChipEnable;

		// Fetch instruction from 0x0
		#10; 
		inst_addr[`InstAddrBus] <= inst_addr[`InstAddrBus] + 4'h4;

		// Fetch instruction from 0x4
		#10; 
		inst_addr[`InstAddrBus] <= inst_addr[`InstAddrBus] + 4'h4;

		// Fetch instruction from 0x8
		#10; 
		inst_addr[`InstAddrBus] <= inst_addr[`InstAddrBus] + 4'h4;

		// Fetch instruction from 0xC
		#10; 
		inst_addr[`InstAddrBus] <= inst_addr[`InstAddrBus] + 4'h4;

		// Fetch instruction from 0x10
		#10; 
		inst_addr[`InstAddrBus] <= inst_addr[`InstAddrBus] + 4'h4;

		// Fetch instruction from 0x14
		#10; 
		inst_addr[`InstAddrBus] <= inst_addr[`InstAddrBus] + 4'h4;
		
		#100 $finish;
	end

endmodule

uniprocessor/Pipeline/tb_InstMem.vcd
$date
	Wed Nov 28 01:47:01 2018
$end
$version
	Icarus Verilog
$end
$timescale
	100ps
$end
$scope module tb_InstMem $end
$var wire 32 ! inst [31:0] $end
$var reg 1 " ce $end
$var reg 32 # inst_addr [31:0] $end
$scope module u0 $end
$var wire 1 " ce $end
$var wire 32 $ inst_addr [31:0] $end
$var wire 6 % inst_mem_index [5:0] $end
$var reg 32 & inst [31:0] $end
$upscope $end
$upscope $end
$enddefinitions $end
#0
$dumpvars
b0 &
b0 %
b0 $
b0 #
0"
b0 !
$end
#100
1"
#200
b10001000100010001000100010001 !
b10001000100010001000100010001 &
b1 %
b100 #
b100 $
#300
b100010001000100010001000100010 !
b100010001000100010001000100010 &
b10 %
b1000 #
b1000 $
#400
b110011001100110011001100110100 !
b110011001100110011001100110100 &
b11 %
b1100 #
b1100 $
#500
b1000100010001000100010001000100 !
b1000100010001000100010001000100 &
b100 %
b10000 #
b10000 $
#600
b11111111111111111111111111111111 !
b11111111111111111111111111111111 &
b101 %
b10100 #
b10100 $
#700
bx !
bx &
b110 %
b11000 #
b11000 $
