uniprocessor/macros/define.v
`define RstEnable  	1'b0	// Reset whilst signal '0'
`define RstDisable 	1'b1 
`define ZeroWord   	32'h0000_0000 
`define ZeroDoubleWord  64'h0000_0000_0000_0000
`define WriteEnable 	1'b1
`define WriteDisable	1'b0
`define ReadEnable	1'b1
`define ReadDisable	1'b0

`define AluControlIn	3:0	// The size of ALU Operation, i.e., ALU control input

`define InstValid	1'b0	// Valid instruction
`define InstInvalid	1'b1	// Invalid instruction
`define True_v		1'b1	// Logically True
`define False_v		1'b0	// Logically False
`define ChipEnable	1'b1
`define ChipDisable	1'b0

// The marcos of RV32I Based instruction
// The 7-bit opcode
`define EXE_ORI	 7'b0_0100_11 // ori 
`define EXE_NOP	 7'b0_0000_00 // nop
`define EXE_BEQ  7'b1_1000_11 // beq
`define EXE_BNE  7'b1_1000_11 // bne
`define EXE_BLT  7'b1_1000_11 // blt
`define EXE_BGE  7'b1_1000_11 // bge
`define EXE_BLTU 7'b1_1000_11 // bltu
`define EXE_BGEU 7'b1_1000_11 // bgeu

`define EXE_ORI 7'b0_0100_11 // ori

// Instruction Memory (ROM) 
`define InstAddrBus 31:0
`define InstAddrWidth 32
`define InstWidth 32
`define InstBus 31:0
`define InstMemNum 131071 // The actual size of ROM is 128KB
`define InstMemNumLog2 17 // The actual size of address

// Register File: regfile
`define RegAddrBus 4:0 // The size of address bus, i.e., 5
`define RegBus 63:0 	   // The size of data bus is 64-bit
`define RegWidth 64      // The data size of each register is 64-bit
`define DoubleRegWidth 128
`define DoubleRegBus 127:0
`define RegNum 32 //  The register from x0 to x31
`define RegNumLog2 5 // The size of address bus, i.e., log 32 base 2 = 5
`define NOPRegAddr 5'b0_0000

uniprocessor/MEM/Register/RegFile.v
`include "../../macros/define.v"

module RegFile (
	input wire sys_clk,
       	input wire rstn,

	input wire [`RegAddrBus] ReadAddr_1,
	input wire [`RegAddrBus] ReadAddr_2,
	input wire [`RegAddrBus] WriteAddr,
	input wire [`RegBus] WriteData,

	input wire RegRead_1, // Enable signal for read operation of first register, i.e., rs1
	input wire RegRead_2, // Enable signal for read operation of second register, i.e., rs2
	input wire RegWrite,  // Enable signal for write-back operation

	output reg [`RegBus] ReadData_1,
	output reg [`RegBus] ReadData_2,

	output [`RegBus] x0, 	
	output [`RegBus] x1, 	
	output [`RegBus] x2, 	
	output [`RegBus] x3, 	
	output [`RegBus] x4, 	
	output [`RegBus] x5, 	
	output [`RegBus] x6, 	
	output [`RegBus] x7, 	
	output [`RegBus] x8, 	
	output [`RegBus] x9, 	
	output [`RegBus] x10, 	
	output [`RegBus] x11, 	
	output [`RegBus] x12, 	
	output [`RegBus] x13, 	
	output [`RegBus] x14, 	
	output [`RegBus] x15, 	
	output [`RegBus] x16, 	
	output [`RegBus] x17, 	
	output [`RegBus] x18, 	
	output [`RegBus] x19, 	
	output [`RegBus] x20, 	
	output [`RegBus] x21, 	
	output [`RegBus] x22, 	
	output [`RegBus] x23, 	
	output [`RegBus] x24, 	
	output [`RegBus] x25, 	
	output [`RegBus] x26, 	
	output [`RegBus] x27, 	
	output [`RegBus] x28, 	
	output [`RegBus] x29, 	
	output [`RegBus] x30, 	
	output [`RegBus] x31 	
);

	// Declaring those 31 general-purpose registers x1 - x31, which hold integer values.
	reg [`RegBus] x_regs[0:`RegNum-1]; 
	assign x0   = x_regs[0]; 
	assign x1   = x_regs[1]; 
	assign x2   = x_regs[2]; 
	assign x3   = x_regs[3]; 
	assign x4   = x_regs[4]; 
	assign x5   = x_regs[5]; 
	assign x6   = x_regs[6]; 
	assign x7   = x_regs[7]; 
	assign x8   = x_regs[8]; 
	assign x9   = x_regs[9]; 
	assign  x10 =  x_regs[10];
	assign  x11 =  x_regs[11];
	assign  x12 =  x_regs[12];
	assign  x13 =  x_regs[13];
	assign  x14 =  x_regs[14];
	assign  x15 =  x_regs[15];
	assign  x16 =  x_regs[16];
	assign  x17 =  x_regs[17];
	assign  x18 =  x_regs[18];
	assign  x19 =  x_regs[19];
	assign  x20 =  x_regs[20];
	assign  x21 =  x_regs[21];
	assign  x22 =  x_regs[22];
	assign  x23 =  x_regs[23];
	assign  x24 =  x_regs[24];
	assign  x25 =  x_regs[25];
	assign  x26 =  x_regs[26];
	assign  x27 =  x_regs[27];
	assign  x28 =  x_regs[28];
	assign  x29 =  x_regs[29];
	assign  x30 =  x_regs[30];
	assign  x31 =  x_regs[31];

	// Only for testbench
	initial begin
		$display("Loading Registers");
		$readmemh("RegRead_pattern.mem", x_regs);
	end

	//==========================================================================================//
	// Read Operation with rs1
	//==========================================================================================//
	always @(*) begin
		if(rstn == `RstEnable)                             ReadData_1[`RegBus] <= `ZeroDoubleWord;	
		else if(ReadAddr_1[`RegAddrBus] == `RegNumLog2'h0) ReadData_1[`RegBus] <= `ZeroDoubleWord; // x0 is hardwired to the constant '0'
		else if(RegRead_1 == `ReadEnable)                  ReadData_1[`RegBus] <= x_regs[ReadAddr_1[`RegAddrBus]]; 
		else if(
			(ReadAddr_1[`RegAddrBus] == WriteAddr[`RegAddrBus]) &&
		        (RegWrite == `WriteEnable) &&
			(RegRead_1 == `ReadEnable)
		)    ReadData_1[`RegBus] <= WriteData[`RegBus]; // for data consistency, bypass the written data to its output
		else ReadData_1[`RegBus] <= `ZeroDoubleWord;
	end	

	//==========================================================================================//
	// Read Operation with rs2
	//==========================================================================================//
	always @(*) begin
		if(rstn == `RstEnable)                             ReadData_2[`RegBus] <= `ZeroDoubleWord;	
		else if(ReadAddr_1[`RegAddrBus] == `RegNumLog2'h0) ReadData_2[`RegBus] <= `ZeroDoubleWord; // x0 is hardwired to the constant '0'
		else if(RegRead_1 == `ReadEnable)                  ReadData_2[`RegBus] <= x_regs[ReadAddr_2[`RegAddrBus]]; 
		else if(
			(ReadAddr_2[`RegAddrBus] == WriteAddr[`RegAddrBus]) &&
		        (RegWrite == `WriteEnable) &&
			(RegRead_2 == `ReadEnable)
		)    ReadData_2[`RegBus] <= WriteData[`RegBus]; // for data consistency, bypass upcoming written data to its output
		else ReadData_2[`RegBus] <= `ZeroDoubleWord;
	end

	//==========================================================================================//
	// Write-Back Operation for rd
	//==========================================================================================//
	always @(posedge sys_clk, rstn) begin
		if(rstn == `RstDisable) begin
		  if(
		  	(RegWrite == `WriteEnable) && 
			(WriteAddr[`RegAddrBus] != `RegNumLog2'h0) // Assigning a new value to register x0 is forbidden 
		  ) x_regs[WriteAddr[`RegAddrBus]] <= WriteData[`RegBus];
		end	
	end

endmodule

uniprocessor/MEM/Register/tb_RegFile.v
`timescale 1ns/100ps
`include "../../macros/define.v"

module tb_RegFile;

	reg sys_clk, rstn;
	reg [`RegAddrBus] ReadAddr_1, ReadAddr_2, WriteAddr;
	reg [`RegBus] WriteData;
	reg RegRead_1, RegRead_2, RegWrite;
	wire [`RegBus] ReadData_1, ReadData_2;
	wire [`RegBus] x_regs[0:`RegNum-1];
	wire [`RegBus] x0; 	
	wire [`RegBus] x1; 	
	wire [`RegBus] x2; 	
	wire [`RegBus] x3; 	
	wire [`RegBus] x4; 	
	wire [`RegBus] x5; 	
	wire [`RegBus] x6; 	
	wire [`RegBus] x7; 	
	wire [`RegBus] x8; 	
	wire [`RegBus] x9; 	
	wire [`RegBus] x10; 	
	wire [`RegBus] x11; 	
	wire [`RegBus] x12; 	
	wire [`RegBus] x13; 	
	wire [`RegBus] x14; 	
	wire [`RegBus] x15; 	
	wire [`RegBus] x16; 	
	wire [`RegBus] x17; 	
	wire [`RegBus] x18; 	
	wire [`RegBus] x19; 	
	wire [`RegBus] x20; 	
	wire [`RegBus] x21; 	
	wire [`RegBus] x22; 	
	wire [`RegBus] x23; 	
	wire [`RegBus] x24; 	
	wire [`RegBus] x25; 	
	wire [`RegBus] x26; 	
	wire [`RegBus] x27; 	
	wire [`RegBus] x28; 	
	wire [`RegBus] x29; 	
	wire [`RegBus] x30; 	
	wire [`RegBus] x31;	

	RegFile u0 (
		.sys_clk (sys_clk),
       		.rstn (rstn),
		.ReadAddr_1 (ReadAddr_1[`RegAddrBus]),
		.ReadAddr_2 (ReadAddr_2[`RegAddrBus]),
		.WriteAddr (WriteAddr[`RegAddrBus]),
		.WriteData (WriteData[`RegBus]),
		.RegRead_1 (RegRead_1), 
		.RegRead_2 (RegRead_2), 
		.RegWrite (RegWrite),  
	
		.ReadData_1 (ReadData_1[`RegBus]),
		.ReadData_2 (ReadData_2[`RegBus]),	
		.x0 (x0), 	
		.x1 (x1), 	
		.x2 (x2), 	
		.x3 (x3), 	
		.x4 (x4), 	
		.x5 (x5), 	
		.x6 (x6), 	
		.x7 (x7), 	
		.x8 (x8), 	
		.x9 (x9), 	
		.x10 (x10), 	
		.x11 (x11), 	
		.x12 (x12), 	
		.x13 (x13), 	
		.x14 (x14), 	
		.x15 (x15), 	
		.x16 (x16), 	
		.x17 (x17), 	
		.x18 (x18), 	
		.x19 (x19), 	
		.x20 (x20), 	
		.x21 (x21), 	
		.x22 (x22), 	
		.x23 (x23), 	
		.x24 (x24), 	
		.x25 (x25), 	
		.x26 (x26), 	
		.x27 (x27), 	
		.x28 (x28), 	
		.x29 (x29), 	
		.x30 (x30), 	
		.x31 (x31) 	
	);
	
	initial begin
		$dumpfile("tb_RegFile.vcd");
		$dumpvars(0, tb_RegFile);
		$monitor("%t: ReadAddr_1: %h, ReadAddr_2: %h, WriteAddr: %h, WriteData: %h, RegRead_1: %h, RegRead_2: %h, RegWrite: %h, ReadData_1: %h, ReadData_2: %h",
				$time,
				ReadAddr_1, ReadAddr_2, WriteAddr,
				WriteData, RegRead_1, RegRead_2, 
				RegWrite, ReadData_1, ReadData_2 
		);
	end

	initial begin
		#0;
		rstn    <= `RstEnable;
		
		#20;
		rstn <= `RstDisable;

		#1000 $finish;
	end

	initial begin
		#0;
		sys_clk <= 1'b0;

		forever #10 sys_clk <= ~sys_clk;
		
		#1000 $finish;
	end

	integer i;
	initial begin
		#0;
		ReadAddr_1 <= 'd0;
		ReadAddr_2 <= 'd31;

		#50 
		ReadAddr_1 <= ReadAddr_1 + 1'b1;
		ReadAddr_2 <= ReadAddr_2 - 1'b1;
		
		for(i = 0; i < 31; i++) begin
			#20 
			ReadAddr_1 <= ReadAddr_1 + 1'b1;
			ReadAddr_2 <= ReadAddr_2 - 1'b1;
		end
		#1000 $finish;

	end

	initial begin
		#0;
		RegRead_1 <= 1'b0;
		RegRead_2 <= 1'b0;

		forever begin
			#10;
			RegRead_1 <= ~RegRead_1;
			RegRead_2 <= ~RegRead_2;
		end	
		#1000 $finish;
	end

	initial begin
		#0   RegWrite <= 1'b0;
		#700 RegWrite <= 1'b1;
		#1000 $finish;
	end

	initial begin
		#0 WriteAddr <= 'd0;
		
		#700;
		for(i = 0; i < 32; i++) begin
			#10
			WriteAddr <= WriteAddr + $itor(i);
		end
		#1000 $finish;
	end

	reg [`RegBus] x_regs_temp[0:`RegNum-1];
	initial begin
		$display("Loading Write Registers");
		$readmemh("RegWrite_pattern.mem", x_regs_temp);
		#1000 $finish;
	end
	initial begin
		#0 RegWrite <= 'd0;
		#700;
		for(i = 0; i < 32; i++) begin
			#10 RegWrite <= x_regs_temp[i];
		end	
		#1000 $finish;
	end

endmodule

uniprocessor/MEM/Register/tb_RegFile.vcd
$date
	Fri Nov 30 17:50:28 2018
$end
$version
	Icarus Verilog
$end
$timescale
	100ps
$end
$scope module tb_RegFile $end
$var wire 64 ! x9 [63:0] $end
$var wire 64 " x8 [63:0] $end
$var wire 64 # x7 [63:0] $end
$var wire 64 $ x6 [63:0] $end
$var wire 64 % x5 [63:0] $end
$var wire 64 & x4 [63:0] $end
$var wire 64 ' x31 [63:0] $end
$var wire 64 ( x30 [63:0] $end
$var wire 64 ) x3 [63:0] $end
$var wire 64 * x29 [63:0] $end
$var wire 64 + x28 [63:0] $end
$var wire 64 , x27 [63:0] $end
$var wire 64 - x26 [63:0] $end
$var wire 64 . x25 [63:0] $end
$var wire 64 / x24 [63:0] $end
$var wire 64 0 x23 [63:0] $end
$var wire 64 1 x22 [63:0] $end
$var wire 64 2 x21 [63:0] $end
$var wire 64 3 x20 [63:0] $end
$var wire 64 4 x2 [63:0] $end
$var wire 64 5 x19 [63:0] $end
$var wire 64 6 x18 [63:0] $end
$var wire 64 7 x17 [63:0] $end
$var wire 64 8 x16 [63:0] $end
$var wire 64 9 x15 [63:0] $end
$var wire 64 : x14 [63:0] $end
$var wire 64 ; x13 [63:0] $end
$var wire 64 < x12 [63:0] $end
$var wire 64 = x11 [63:0] $end
$var wire 64 > x10 [63:0] $end
$var wire 64 ? x1 [63:0] $end
$var wire 64 @ x0 [63:0] $end
$var wire 64 A ReadData_2 [63:0] $end
$var wire 64 B ReadData_1 [63:0] $end
$var reg 5 C ReadAddr_1 [4:0] $end
$var reg 5 D ReadAddr_2 [4:0] $end
$var reg 1 E RegRead_1 $end
$var reg 1 F RegRead_2 $end
$var reg 1 G RegWrite $end
$var reg 5 H WriteAddr [4:0] $end
$var reg 64 I WriteData [63:0] $end
$var reg 1 J rstn $end
$var reg 1 K sys_clk $end
$var integer 32 L i [31:0] $end
$scope module u0 $end
$var wire 5 M ReadAddr_1 [4:0] $end
$var wire 5 N ReadAddr_2 [4:0] $end
$var wire 1 E RegRead_1 $end
$var wire 1 F RegRead_2 $end
$var wire 1 G RegWrite $end
$var wire 5 O WriteAddr [4:0] $end
$var wire 64 P WriteData [63:0] $end
$var wire 1 J rstn $end
$var wire 1 K sys_clk $end
$var wire 64 Q x0 [63:0] $end
$var wire 64 R x1 [63:0] $end
$var wire 64 S x10 [63:0] $end
$var wire 64 T x11 [63:0] $end
$var wire 64 U x12 [63:0] $end
$var wire 64 V x13 [63:0] $end
$var wire 64 W x14 [63:0] $end
$var wire 64 X x15 [63:0] $end
$var wire 64 Y x16 [63:0] $end
$var wire 64 Z x17 [63:0] $end
$var wire 64 [ x18 [63:0] $end
$var wire 64 \ x19 [63:0] $end
$var wire 64 ] x2 [63:0] $end
$var wire 64 ^ x20 [63:0] $end
$var wire 64 _ x21 [63:0] $end
$var wire 64 ` x22 [63:0] $end
$var wire 64 a x23 [63:0] $end
$var wire 64 b x24 [63:0] $end
$var wire 64 c x25 [63:0] $end
$var wire 64 d x26 [63:0] $end
$var wire 64 e x27 [63:0] $end
$var wire 64 f x28 [63:0] $end
$var wire 64 g x29 [63:0] $end
$var wire 64 h x3 [63:0] $end
$var wire 64 i x30 [63:0] $end
$var wire 64 j x31 [63:0] $end
$var wire 64 k x4 [63:0] $end
$var wire 64 l x5 [63:0] $end
$var wire 64 m x6 [63:0] $end
$var wire 64 n x7 [63:0] $end
$var wire 64 o x8 [63:0] $end
$var wire 64 p x9 [63:0] $end
$var reg 64 q ReadData_1 [63:0] $end
$var reg 64 r ReadData_2 [63:0] $end
$upscope $end
$upscope $end
$enddefinitions $end
#0
$dumpvars
b0 r
b0 q
b1001100110011001100110011001100110011001100110011001100110011001 p
b1000100010001000100010001000100010001000100010001000100010001000 o
b111011101110111011101110111011101110111011101110111011101110111 n
b110011001100110011001100110011001100110011001100110011001100110 m
b101010101010101010101010101010101010101010101010101010101010101 l
b100010001000100010001000100010001000100010001000100010001000100 k
b1111111111111111111111111111111111111111111111111111111111111111 j
b1110111011101110111011101110111011101110111011101110111011101110 i
b11001100110011001100110011001100110011001100110011001100110011 h
b1101110111011101110111011101110111011101110111011101110111011101 g
b1100110011001100110011001100110011001100110011001100110011001100 f
b1011101110111011101110111011101110111011101110111011101110111011 e
b1010101010101010101010101010101010101010101010101010101010101010 d
b1001100110011001100110011001100110011001100110011001100110011001 c
b1000100010001000100010001000100010001000100010001000100010001000 b
b111011101110111011101110111011101110111011101110111011101110111 a
b110011001100110011001100110011001100110011001100110011001100110 `
b101010101010101010101010101010101010101010101010101010101010101 _
b100010001000100010001000100010001000100010001000100010001000100 ^
b10001000100010001000100010001000100010001000100010001000100010 ]
b11001100110011001100110011001100110011001100110011001100110011 \
b10001000100010001000100010001000100010001000100010001000100010 [
b1000100010001000100010001000100010001000100010001000100010001 Z
b0 Y
b1111111111111111111111111111111111111111111111111111111111111111 X
b1110111011101110111011101110111011101110111011101110111011101110 W
b1101110111011101110111011101110111011101110111011101110111011101 V
b1100110011001100110011001100110011001100110011001100110011001100 U
b1011101110111011101110111011101110111011101110111011101110111011 T
b1010101010101010101010101010101010101010101010101010101010101010 S
b1000100010001000100010001000100010001000100010001000100010001 R
b0 Q
bx P
b0 O
b11111 N
b0 M
bx L
0K
0J
bx I
b0 H
0G
0F
0E
b11111 D
b0 C
b0 B
b0 A
b0 @
b1000100010001000100010001000100010001000100010001000100010001 ?
b1010101010101010101010101010101010101010101010101010101010101010 >
b1011101110111011101110111011101110111011101110111011101110111011 =
b1100110011001100110011001100110011001100110011001100110011001100 <
b1101110111011101110111011101110111011101110111011101110111011101 ;
b1110111011101110111011101110111011101110111011101110111011101110 :
b1111111111111111111111111111111111111111111111111111111111111111 9
b0 8
b1000100010001000100010001000100010001000100010001000100010001 7
b10001000100010001000100010001000100010001000100010001000100010 6
b11001100110011001100110011001100110011001100110011001100110011 5
b10001000100010001000100010001000100010001000100010001000100010 4
b100010001000100010001000100010001000100010001000100010001000100 3
b101010101010101010101010101010101010101010101010101010101010101 2
b110011001100110011001100110011001100110011001100110011001100110 1
b111011101110111011101110111011101110111011101110111011101110111 0
b1000100010001000100010001000100010001000100010001000100010001000 /
b1001100110011001100110011001100110011001100110011001100110011001 .
b1010101010101010101010101010101010101010101010101010101010101010 -
b1011101110111011101110111011101110111011101110111011101110111011 ,
b1100110011001100110011001100110011001100110011001100110011001100 +
b1101110111011101110111011101110111011101110111011101110111011101 *
b11001100110011001100110011001100110011001100110011001100110011 )
b1110111011101110111011101110111011101110111011101110111011101110 (
b1111111111111111111111111111111111111111111111111111111111111111 '
b100010001000100010001000100010001000100010001000100010001000100 &
b101010101010101010101010101010101010101010101010101010101010101 %
b110011001100110011001100110011001100110011001100110011001100110 $
b111011101110111011101110111011101110111011101110111011101110111 #
b1000100010001000100010001000100010001000100010001000100010001000 "
b1001100110011001100110011001100110011001100110011001100110011001 !
$end
#100
1F
1E
1K
#200
0F
0E
0K
1J
#300
1F
1E
1K
#400
0F
0E
0K
#500
b1110111011101110111011101110111011101110111011101110111011101110 A
b1110111011101110111011101110111011101110111011101110111011101110 r
b1000100010001000100010001000100010001000100010001000100010001 B
b1000100010001000100010001000100010001000100010001000100010001 q
1F
1E
1K
b11110 D
b11110 N
b1 C
b1 M
b0 L
#600
b0 A
b0 r
b0 B
b0 q
0F
0E
0K
#700
b1101110111011101110111011101110111011101110111011101110111011101 A
b1101110111011101110111011101110111011101110111011101110111011101 r
b10001000100010001000100010001000100010001000100010001000100010 B
b10001000100010001000100010001000100010001000100010001000100010 q
1F
1E
1K
b11101 D
b11101 N
b10 C
b10 M
b1 L
#800
b0 A
b0 r
b0 B
b0 q
0F
0E
0K
#900
b1100110011001100110011001100110011001100110011001100110011001100 A
b1100110011001100110011001100110011001100110011001100110011001100 r
b11001100110011001100110011001100110011001100110011001100110011 B
b11001100110011001100110011001100110011001100110011001100110011 q
1F
1E
1K
b11100 D
b11100 N
b11 C
b11 M
b10 L
#1000
b0 A
b0 r
b0 B
b0 q
0F
0E
0K
#1100
b1011101110111011101110111011101110111011101110111011101110111011 A
b1011101110111011101110111011101110111011101110111011101110111011 r
b100010001000100010001000100010001000100010001000100010001000100 B
b100010001000100010001000100010001000100010001000100010001000100 q
1F
1E
1K
b11011 D
b11011 N
b100 C
b100 M
b11 L
#1200
b0 A
b0 r
b0 B
b0 q
0F
0E
0K
#1300
b1010101010101010101010101010101010101010101010101010101010101010 A
b1010101010101010101010101010101010101010101010101010101010101010 r
b101010101010101010101010101010101010101010101010101010101010101 B
b101010101010101010101010101010101010101010101010101010101010101 q
1F
1E
1K
b11010 D
b11010 N
b101 C
b101 M
b100 L
#1400
b0 A
b0 r
b0 B
b0 q
0F
0E
0K
#1500
b1001100110011001100110011001100110011001100110011001100110011001 A
b1001100110011001100110011001100110011001100110011001100110011001 r
b110011001100110011001100110011001100110011001100110011001100110 B
b110011001100110011001100110011001100110011001100110011001100110 q
1F
1E
1K
b11001 D
b11001 N
b110 C
b110 M
b101 L
#1600
b0 A
b0 r
b0 B
b0 q
0F
0E
0K
#1700
b1000100010001000100010001000100010001000100010001000100010001000 A
b1000100010001000100010001000100010001000100010001000100010001000 r
b111011101110111011101110111011101110111011101110111011101110111 B
b111011101110111011101110111011101110111011101110111011101110111 q
1F
1E
1K
b11000 D
b11000 N
b111 C
b111 M
b110 L
#1800
b0 A
b0 r
b0 B
b0 q
0F
0E
0K
#1900
b111011101110111011101110111011101110111011101110111011101110111 A
b111011101110111011101110111011101110111011101110111011101110111 r
b1000100010001000100010001000100010001000100010001000100010001000 B
b1000100010001000100010001000100010001000100010001000100010001000 q
1F
1E
1K
b10111 D
b10111 N
b1000 C
b1000 M
b111 L
#2000
b0 A
b0 r
b0 B
b0 q
0F
0E
0K
#2100
b110011001100110011001100110011001100110011001100110011001100110 A
b110011001100110011001100110011001100110011001100110011001100110 r
b1001100110011001100110011001100110011001100110011001100110011001 B
b1001100110011001100110011001100110011001100110011001100110011001 q
1F
1E
1K
b10110 D
b10110 N
b1001 C
b1001 M
b1000 L
#2200
b0 A
b0 r
b0 B
b0 q
0F
0E
0K
#2300
b101010101010101010101010101010101010101010101010101010101010101 A
b101010101010101010101010101010101010101010101010101010101010101 r
b1010101010101010101010101010101010101010101010101010101010101010 B
b1010101010101010101010101010101010101010101010101010101010101010 q
1F
1E
1K
b10101 D
b10101 N
b1010 C
b1010 M
b1001 L
#2400
b0 A
b0 r
b0 B
b0 q
0F
0E
0K
#2500
b100010001000100010001000100010001000100010001000100010001000100 A
b100010001000100010001000100010001000100010001000100010001000100 r
b1011101110111011101110111011101110111011101110111011101110111011 B
b1011101110111011101110111011101110111011101110111011101110111011 q
1F
1E
1K
b10100 D
b10100 N
b1011 C
b1011 M
b1010 L
#2600
b0 A
b0 r
b0 B
b0 q
0F
0E
0K
#2700
b11001100110011001100110011001100110011001100110011001100110011 A
b11001100110011001100110011001100110011001100110011001100110011 r
b1100110011001100110011001100110011001100110011001100110011001100 B
b1100110011001100110011001100110011001100110011001100110011001100 q
1F
1E
1K
b10011 D
b10011 N
b1100 C
b1100 M
b1011 L
#2800
b0 A
b0 r
b0 B
b0 q
0F
0E
0K
#2900
b10001000100010001000100010001000100010001000100010001000100010 A
b10001000100010001000100010001000100010001000100010001000100010 r
b1101110111011101110111011101110111011101110111011101110111011101 B
b1101110111011101110111011101110111011101110111011101110111011101 q
1F
1E
1K
b10010 D
b10010 N
b1101 C
b1101 M
b1100 L
#3000
b0 A
b0 r
b0 B
b0 q
0F
0E
0K
#3100
b1000100010001000100010001000100010001000100010001000100010001 A
b1000100010001000100010001000100010001000100010001000100010001 r
b1110111011101110111011101110111011101110111011101110111011101110 B
b1110111011101110111011101110111011101110111011101110111011101110 q
1F
1E
1K
b10001 D
b10001 N
b1110 C
b1110 M
b1101 L
#3200
b0 A
b0 r
b0 B
b0 q
0F
0E
0K
#3300
b1111111111111111111111111111111111111111111111111111111111111111 B
b1111111111111111111111111111111111111111111111111111111111111111 q
1F
1E
1K
b10000 D
b10000 N
b1111 C
b1111 M
b1110 L
#3400
b0 B
b0 q
0F
0E
0K
#3500
b1111111111111111111111111111111111111111111111111111111111111111 A
b1111111111111111111111111111111111111111111111111111111111111111 r
1F
1E
1K
b1111 D
b1111 N
b10000 C
b10000 M
b1111 L
#3600
b0 A
b0 r
0F
0E
0K
#3700
b1110111011101110111011101110111011101110111011101110111011101110 A
b1110111011101110111011101110111011101110111011101110111011101110 r
b1000100010001000100010001000100010001000100010001000100010001 B
b1000100010001000100010001000100010001000100010001000100010001 q
1F
1E
1K
b1110 D
b1110 N
b10001 C
b10001 M
b10000 L
#3800
b0 A
b0 r
b0 B
b0 q
0F
0E
0K
#3900
b1101110111011101110111011101110111011101110111011101110111011101 A
b1101110111011101110111011101110111011101110111011101110111011101 r
b10001000100010001000100010001000100010001000100010001000100010 B
b10001000100010001000100010001000100010001000100010001000100010 q
1F
1E
1K
b1101 D
b1101 N
b10010 C
b10010 M
b10001 L
#4000
b0 A
b0 r
b0 B
b0 q
0F
0E
0K
#4100
b1100110011001100110011001100110011001100110011001100110011001100 A
b1100110011001100110011001100110011001100110011001100110011001100 r
b11001100110011001100110011001100110011001100110011001100110011 B
b11001100110011001100110011001100110011001100110011001100110011 q
1F
1E
1K
b1100 D
b1100 N
b10011 C
b10011 M
b10010 L
#4200
b0 A
b0 r
b0 B
b0 q
0F
0E
0K
#4300
b1011101110111011101110111011101110111011101110111011101110111011 A
b1011101110111011101110111011101110111011101110111011101110111011 r
b100010001000100010001000100010001000100010001000100010001000100 B
b100010001000100010001000100010001000100010001000100010001000100 q
1F
1E
1K
b1011 D
b1011 N
b10100 C
b10100 M
b10011 L
#4400
b0 A
b0 r
b0 B
b0 q
0F
0E
0K
#4500
b1010101010101010101010101010101010101010101010101010101010101010 A
b1010101010101010101010101010101010101010101010101010101010101010 r
b101010101010101010101010101010101010101010101010101010101010101 B
b101010101010101010101010101010101010101010101010101010101010101 q
1F
1E
1K
b1010 D
b1010 N
b10101 C
b10101 M
b10100 L
#4600
b0 A
b0 r
b0 B
b0 q
0F
0E
0K
#4700
b1001100110011001100110011001100110011001100110011001100110011001 A
b1001100110011001100110011001100110011001100110011001100110011001 r
b110011001100110011001100110011001100110011001100110011001100110 B
b110011001100110011001100110011001100110011001100110011001100110 q
1F
1E
1K
b1001 D
b1001 N
b10110 C
b10110 M
b10101 L
#4800
b0 A
b0 r
b0 B
b0 q
0F
0E
0K
#4900
b1000100010001000100010001000100010001000100010001000100010001000 A
b1000100010001000100010001000100010001000100010001000100010001000 r
b111011101110111011101110111011101110111011101110111011101110111 B
b111011101110111011101110111011101110111011101110111011101110111 q
1F
1E
1K
b1000 D
b1000 N
b10111 C
b10111 M
b10110 L
#5000
b0 A
b0 r
b0 B
b0 q
0F
0E
0K
#5100
b111011101110111011101110111011101110111011101110111011101110111 A
b111011101110111011101110111011101110111011101110111011101110111 r
b1000100010001000100010001000100010001000100010001000100010001000 B
b1000100010001000100010001000100010001000100010001000100010001000 q
1F
1E
1K
b111 D
b111 N
b11000 C
b11000 M
b10111 L
#5200
b0 A
b0 r
b0 B
b0 q
0F
0E
0K
#5300
b110011001100110011001100110011001100110011001100110011001100110 A
b110011001100110011001100110011001100110011001100110011001100110 r
b1001100110011001100110011001100110011001100110011001100110011001 B
b1001100110011001100110011001100110011001100110011001100110011001 q
1F
1E
1K
b110 D
b110 N
b11001 C
b11001 M
b11000 L
#5400
b0 A
b0 r
b0 B
b0 q
0F
0E
0K
#5500
b101010101010101010101010101010101010101010101010101010101010101 A
b101010101010101010101010101010101010101010101010101010101010101 r
b1010101010101010101010101010101010101010101010101010101010101010 B
b1010101010101010101010101010101010101010101010101010101010101010 q
1F
1E
1K
b101 D
b101 N
b11010 C
b11010 M
b11001 L
#5600
b0 A
b0 r
b0 B
b0 q
0F
0E
0K
#5700
b100010001000100010001000100010001000100010001000100010001000100 A
b100010001000100010001000100010001000100010001000100010001000100 r
b1011101110111011101110111011101110111011101110111011101110111011 B
b1011101110111011101110111011101110111011101110111011101110111011 q
1F
1E
1K
b100 D
b100 N
b11011 C
b11011 M
b11010 L
#5800
b0 A
b0 r
b0 B
b0 q
0F
0E
0K
#5900
b11001100110011001100110011001100110011001100110011001100110011 A
b11001100110011001100110011001100110011001100110011001100110011 r
b1100110011001100110011001100110011001100110011001100110011001100 B
b1100110011001100110011001100110011001100110011001100110011001100 q
1F
1E
1K
b11 D
b11 N
b11100 C
b11100 M
b11011 L
#6000
b0 A
b0 r
b0 B
b0 q
0F
0E
0K
#6100
b10001000100010001000100010001000100010001000100010001000100010 A
b10001000100010001000100010001000100010001000100010001000100010 r
b1101110111011101110111011101110111011101110111011101110111011101 B
b1101110111011101110111011101110111011101110111011101110111011101 q
1F
1E
1K
b10 D
b10 N
b11101 C
b11101 M
b11100 L
#6200
b0 A
b0 r
b0 B
b0 q
0F
0E
0K
#6300
b1000100010001000100010001000100010001000100010001000100010001 A
b1000100010001000100010001000100010001000100010001000100010001 r
b1110111011101110111011101110111011101110111011101110111011101110 B
b1110111011101110111011101110111011101110111011101110111011101110 q
1F
1E
1K
b1 D
b1 N
b11110 C
b11110 M
b11101 L
#6400
b0 A
b0 r
b0 B
b0 q
0F
0E
0K
#6500
b1111111111111111111111111111111111111111111111111111111111111111 B
b1111111111111111111111111111111111111111111111111111111111111111 q
1F
1E
1K
b0 D
b0 N
b11111 C
b11111 M
b11110 L
#6600
b0 B
b0 q
0F
0E
0K
#6700
1F
1E
1K
b11111 D
b11111 N
b0 C
b0 M
b11111 L
#6800
0F
0E
0K
#6900
1F
1E
1K
#7000
0F
0E
0K
1G
b0 L
#7100
1F
1E
1K
0G
b10 L
#7200
0F
0E
0K
1G
b10 H
b10 O
b100 L
#7300
1F
1E
1K
0G
b110 H
b110 O
b110 L
#7400
0F
0E
0K
1G
b1100 H
b1100 O
b1000 L
#7500
bx 3
bx ^
1F
1E
1K
b10100 H
b10100 O
b1010 L
#7600
0F
0E
0K
0G
b11110 H
b11110 O
b1100 L
#7700
1F
1E
1K
b1010 H
b1010 O
b1110 L
#7800
0F
0E
0K
b11000 H
b11000 O
b10000 L
#7900
bx "
bx o
1F
1E
1K
1G
b1000 H
b1000 O
b10010 L
#8000
0F
0E
0K
0G
b11010 H
b11010 O
b10100 L
#8100
bx :
bx W
1F
1E
1K
1G
b1110 H
b1110 O
b10110 L
#8200
0F
0E
0K
0G
b100 H
b100 O
b11000 L
