uniprocessor/macros/define.v
`define RstEnable  	1'b0	// Reset whilst signal '0'
`define RstDisable 	1'b1 
`define ZeroWord   	32'h0000_0000 
`define ZeroDoubleWord  64'h0000_0000_0000_0000
`define WriteEnable 	1'b1
`define WriteDisable	1'b0
`define ReadEnable	1'b1
`define ReadDisable	1'b0

`define AluControlIn	3:0	// The size of ALU Operation, i.e., ALU control input

`define InstValid	1'b0	// Valid instruction
`define InstInvalid	1'b1	// Invalid instruction
`define True_v		1'b1	// Logically True
`define False_v		1'b0	// Logically False
`define ChipEnable	1'b1
`define ChipDisable	1'b0

// The marcos of RV32I Based instruction
// The 7-bit opcode
`define EXE_ORI	 7'b0_0100_11 // ori 
`define EXE_NOP	 7'b0_0000_00 // nop
`define EXE_BEQ  7'b1_1000_11 // beq
`define EXE_BNE  7'b1_1000_11 // bne
`define EXE_BLT  7'b1_1000_11 // blt
`define EXE_BGE  7'b1_1000_11 // bge
`define EXE_BLTU 7'b1_1000_11 // bltu
`define EXE_BGEU 7'b1_1000_11 // bgeu

`define EXE_ORI 7'b0_0100_11 // ori

// Instruction Memory (ROM) 
`define InstAddrBus 31:0
`define InstAddrWidth 32
`define InstWidth 32
`define InstBus 31:0
`define InstMemNum 131071 // The actual size of ROM is 128KB
`define InstMemNumLog2 17 // The actual size of address

// Register File: regfile
`define RegAddrBus 4:0 // The size of address bus, i.e., 5
`define RegBus 63:0 	   // The size of data bus is 64-bit
`define RegWidth 64      // The data size of each register is 64-bit
`define DoubleRegWidth 128
`define DoubleRegBus 127:0
`define RegNum 32 //  The register from x0 to x31
`define RegNumLog2 5 // The size of address bus, i.e., log 32 base 2 = 5
`define NOPRegAddr 5'b0_0000

uniprocessor/PC/pc.v
`include "../macros/define.v"

module pc (
	
	input wire sys_clk,
	input wire rstn,

	output reg [`InstAddrBus] pc_addr, // Point the memory address of current instruction inside the instruction memory (32-bit instruction)
	output reg	 ce // Enable the instruction memory to be accessable 
);

	always@ (posedge sys_clk, rstn)
	begin
		if(rstn == `RstEnable) ce <= `ChipDisable;
		else		       ce <= `ChipEnable;
	end

	always@ (posedge sys_clk, rstn)
	begin
		if(rstn == `RstEnable && ce == `ChipDisable ) 
			pc_addr[`InstAddrBus] <= `InstAddrWidth'd0;
		else
			pc_addr[`InstAddrBus] <= pc_addr[`InstAddrBus] + 4'h4;
			
	end

endmodule

uniprocessor/PC/tb_pc.v
//`timescale 1ns/100ps 

`include "../macros/define.v"

module tb_pc;

	reg sys_clk, rstn;
	wire [`InstAddrBus] pc_addr;
	wire ce;

	pc u0 (	
		 .sys_clk 	(sys_clk),
		 .rstn		(rstn),	
		 .pc_addr  (pc_addr[`InstAddrBus]), 
		 .ce          (ce)
	);
	
	initial begin
		$dumpfile("tb_pc.vcd");
		$dumpvars(0, tb_pc);
		//$timeformat(-9, 2, " ns", 20); // Print %t with scaled in ns (-9) with 2 precision digits
		$monitor("%t: pc_addr = %b, ce = %h", $time, pc_addr[`InstAddrBus], ce);
	end

	initial begin
		#0;
		rstn    <= `RstEnable;
		
		#100;
		rstn <= `RstDisable;

		#300 $finish;
	end

	initial begin
		#0;
		sys_clk <= 1'b0;

		forever #10 sys_clk <= ~sys_clk;
		
		#300 $finish;
	end

endmodule

uniprocessor/PC/tb_pc.vcd
$date
	Fri Jul 19 17:22:00 2019
$end

$version
	Synopsys VCS version N-2017.12-SP2_Full64
$end

$timescale
	1s
$end

$comment Csum: 1 ad8f8fd27dc2b7c5 $end


$scope module tb_pc $end
$var reg 1 ! sys_clk $end
$var reg 1 " rstn $end
$var wire 32 # pc_addr [31:0] $end
$var wire 1 $ ce $end

$scope module u0 $end
$var wire 1 ! sys_clk $end
$var wire 1 " rstn $end
$var reg 32 # pc_addr [31:0] $end
$var reg 1 $ ce $end
$upscope $end

$upscope $end

$enddefinitions $end

#0
$dumpvars
0"
0!
0$
bxxxxxxxxxxxxxxxxxxxxxxxxxxxxxxxx #
$end
#10
1!
b00000000000000000000000000000000 #
#20
0!
#30
1!
#40
0!
#50
1!
#60
0!
#70
1!
#80
0!
#90
1!
#100
1"
0!
1$
b00000000000000000000000000000100 #
#110
1!
b00000000000000000000000000001000 #
#120
0!
#130
1!
b00000000000000000000000000001100 #
#140
0!
#150
1!
b00000000000000000000000000010000 #
#160
0!
#170
1!
b00000000000000000000000000010100 #
#180
0!
#190
1!
b00000000000000000000000000011000 #
#200
0!
#210
1!
b00000000000000000000000000011100 #
#220
0!
#230
1!
b00000000000000000000000000100000 #
#240
0!
#250
1!
b00000000000000000000000000100100 #
#260
0!
#270
1!
b00000000000000000000000000101000 #
#280
0!
#290
1!
b00000000000000000000000000101100 #
#300
0!
#310
1!
b00000000000000000000000000110000 #
#320
0!
#330
1!
b00000000000000000000000000110100 #
#340
0!
#350
1!
b00000000000000000000000000111000 #
#360
0!
#370
1!
b00000000000000000000000000111100 #
#380
0!
#390
1!
b00000000000000000000000001000000 #
