uniprocessor/macros/define.v
`define RstEnable  	1'b0	// Reset whilst signal '0'
`define RstDisable 	1'b1 
`define ZeroWord   	32'h0000_0000 
`define ZeroDoubleWord  64'h0000_0000_0000_0000
`define WriteEnable 	1'b1
`define WriteDisable	1'b0
`define ReadEnable	1'b1
`define ReadDisable	1'b0

`define AluControlIn	3:0	// The size of ALU Operation, i.e., ALU control input

`define InstValid	1'b0	// Valid instruction
`define InstInvalid	1'b1	// Invalid instruction
`define True_v		1'b1	// Logically True
`define False_v		1'b0	// Logically False
`define ChipEnable	1'b1
`define ChipDisable	1'b0

// The marcos of RV32I Based instruction
// The 7-bit opcode
`define EXE_ORI	 7'b0_0100_11 // ori 
`define EXE_NOP	 7'b0_0000_00 // nop
`define EXE_BEQ  7'b1_1000_11 // beq
`define EXE_BNE  7'b1_1000_11 // bne
`define EXE_BLT  7'b1_1000_11 // blt
`define EXE_BGE  7'b1_1000_11 // bge
`define EXE_BLTU 7'b1_1000_11 // bltu
`define EXE_BGEU 7'b1_1000_11 // bgeu

`define EXE_ORI 7'b0_0100_11 // ori

// Instruction Memory (ROM) 
`define InstAddrBus 31:0
`define InstAddrWidth 32
`define InstWidth 32
`define InstBus 31:0
`define InstMemNum 131071 // The actual size of ROM is 128KB
`define InstMemNumLog2 17 // The actual size of address

// Register File: regfile
`define RegAddrBus 4:0 // The size of address bus, i.e., 5
`define RegBus 63:0 	   // The size of data bus is 64-bit
`define RegWidth 64      // The data size of each register is 64-bit
`define DoubleRegWidth 128
`define DoubleRegBus 127:0
`define RegNum 32 //  The register from x0 to x31
`define RegNumLog2 5 // The size of address bus, i.e., log 32 base 2 = 5
`define NOPRegAddr 5'b0_0000

uniprocessor/PC/pc.v
`include "../macros/define.v"

module pc (
	
	input wire sys_clk,
	input wire rstn,

	output reg [`InstAddrBus] pc_addr, // Point the memory address of current instruction inside the instruction memory (32-bit instruction)
	output reg	 ce // Enable the instruction memory to be accessable 
);

	always@ (posedge sys_clk, rstn)
	begin
		if(rstn == `RstEnable) ce <= `ChipDisable;
		else		       ce <= `ChipEnable;
	end

	always@ (posedge sys_clk, rstn)
	begin
		if(rstn == `RstEnable && ce == `ChipDisable ) 
			pc_addr[`InstAddrBus] <= `InstAddrWidth'd0;
		else
			pc_addr[`InstAddrBus] <= pc_addr[`InstAddrBus] + 4'h4;
			
	end

endmodule

uniprocessor/PC/tb_pc.v
`timescale 1ns/100ps 

`include "../macros/define.v"

module tb_pc;

	reg sys_clk, rstn;
	wire [`InstAddrBus] pc_addr;
	wire ce;

	pc u0 (	
		 .sys_clk 	(sys_clk),
		 .rstn		(rstn),	
		 .pc_addr  (pc_addr[`InstAddrBus]), 
		 .ce          (ce)
	);
	
	initial begin
		$dumpfile("tb_pc.vcd");
		$dumpvars(0, tb_pc);
		//$timeformat(-9, 2, " ns", 20); // Print %t with scaled in ns (-9) with 2 precision digits
		$monitor("%t: pc_addr = %b, ce = %h", $time, pc_addr[`InstAddrBus], ce);
	end

	initial begin
		#0;
		rstn    <= `RstEnable;
		
		#100;
		rstn <= `RstDisable;

		#300 $finish;
	end

	initial begin
		#0;
		sys_clk <= 1'b0;

		forever #10 sys_clk <= ~sys_clk;
		
		#300 $finish;
	end

endmodule

uniprocessor/PC/tb_pc.vcd
$date
	Tue Nov 27 22:52:28 2018
$end
$version
	Icarus Verilog
$end
$timescale
	100ps
$end
$scope module tb_pc $end
$var wire 32 ! pc_addr [31:0] $end
$var wire 1 " ce $end
$var reg 1 # rstn $end
$var reg 1 $ sys_clk $end
$scope module u0 $end
$var wire 1 # rstn $end
$var wire 1 $ sys_clk $end
$var reg 1 " ce $end
$var reg 32 % pc_addr [31:0] $end
$upscope $end
$upscope $end
$enddefinitions $end
#0
$dumpvars
bx %
0$
0#
0"
bx !
$end
#100
b0 !
b0 %
1$
#200
0$
#300
1$
#400
0$
#500
1$
#600
0$
#700
1$
#800
0$
#900
1$
#1000
1"
b100 !
b100 %
0$
1#
#1100
b1000 !
b1000 %
1$
#1200
0$
#1300
b1100 !
b1100 %
1$
#1400
0$
#1500
b10000 !
b10000 %
1$
#1600
0$
#1700
b10100 !
b10100 %
1$
#1800
0$
#1900
b11000 !
b11000 %
1$
#2000
0$
#2100
b11100 !
b11100 %
1$
#2200
0$
#2300
b100000 !
b100000 %
1$
#2400
0$
#2500
b100100 !
b100100 %
1$
#2600
0$
#2700
b101000 !
b101000 %
1$
#2800
0$
#2900
b101100 !
b101100 %
1$
#3000
0$
#3100
b110000 !
b110000 %
1$
#3200
0$
#3300
b110100 !
b110100 %
1$
#3400
0$
#3500
b111000 !
b111000 %
1$
#3600
0$
#3700
b111100 !
b111100 %
1$
#3800
0$
#3900
b1000000 !
b1000000 %
1$
